AUTHORS.txt
LICENSE.txt
MANIFEST.in
README
setup.py
django_preview.egg-info/PKG-INFO
django_preview.egg-info/SOURCES.txt
django_preview.egg-info/dependency_links.txt
django_preview.egg-info/top_level.txt
preview/__init__.py
preview/admin.py
preview/forms.py
preview/listeners.py
preview/managers.py
preview/models.py
preview/urls.py
preview/views.py
preview/templates/preview/confirm.html
preview/templates/preview/email.txt
preview/templates/preview/email_subject.txt
preview/templates/preview/signup.html
preview/templates/preview/unsignup.html