Metadata-Version: 1.0
Name: django-preview
Version: 0.1
Summary: Managing preview subscription in Django
Home-page: https://github.com/volodymyrko/django-preview
Author: Kovtun Volodymyr
Author-email: vova-zms@yandex.ua
License: BSD
Download-URL: https://github.com/volodymyrko/django-preview
Platform: UNKNOWN
Classifier: Framework :: Django
Classifier: Intended Audience :: Developers
Classifier: Intended Audience :: System Administrators
Classifier: Operating System :: OS Independent
Classifier: Topic :: Software Development
